ktcalendars/__init__.py
ktcalendars-0.9.1.dist-info/METADATA
ktcalendars-0.9.1.dist-info/WHEEL
ktcalendars-0.9.1.dist-info/licenses/LICENSE.md
ktcalendars-0.9.1.dist-info/licenses/NOTICE.md
ktcalendars-0.9.1.dist-info/RECORD
