Metadata-Version: 2.4
Name: ktcalendars
Version: 0.9.1
License-Expression: Apache-2.0
License-File: LICENSE.md
License-File: NOTICE.md
Classifier: Programming Language :: Python :: 3 :: Only
Classifier: Programming Language :: Python :: 3.10
Classifier: Programming Language :: Python :: 3.11
Classifier: Programming Language :: Python :: 3.12
Classifier: Programming Language :: Python :: 3.13
Requires-Python: >=3.10
Requires-Dist: holidays
